[
  {
    "delivery_id": "4d0fbed0-f1bd-4b43-88da-db3a2aa7e167",
    "vendor_id": "f96ed92f-cac6-42b9-816e-583ba91a77ec",
    "vendor_name": "ProTech Safety Gear - Q",
    "delivery_date": "2025-09-10",
    "items_delivered": "Breathing Apparatus",
    "quantity": 11,
    "on_time_status": true,
    "quality_score": 4.53,
    "defect_count": 1,
    "issue_description": ""
  },
  {
    "delivery_id": "a7374aea-5c20-4da1-8b60-87967b3158b4",
    "vendor_id": "af157658-9e1c-4dc4-980d-4426b95a344e",
    "vendor_name": "Blaze Control Systems - A",
    "delivery_date": "2025-02-22",
    "items_delivered": "Protective Gear",
    "quantity": 438,
    "on_time_status": true,
    "quality_score": 4.51,
    "defect_count": 1,
    "issue_description": ""
  },
  {
    "delivery_id": "c8927bf1-d966-4fd4-92ff-156756aa960b",
    "vendor_id": "8023d5ed-e138-4114-9b33-5b078e94c4aa",
    "vendor_name": "SecureLife Fire Systems - C",
    "delivery_date": "2025-10-04",
    "items_delivered": "Fire Hoses",
    "quantity": 104,
    "on_time_status": true,
    "quality_score": 3.54,
    "defect_count": 0,
    "issue_description": ""
  },
  {
    "delivery_id": "a9accfe3-9b2a-4dec-87cc-9cf33799f2ed",
    "vendor_id": "7a522c24-b040-4be9-a9be-ac1b92af655a",
    "vendor_name": "Blaze Control Systems - C",
    "delivery_date": "2025-07-04",
    "items_delivered": "Protective Gear",
    "quantity": 408,
    "on_time_status": false,
    "quality_score": 4.66,
    "defect_count": 1,
    "issue_description": "No issues"
  },
  {
    "delivery_id": "eae0ffdc-67f6-474a-80d7-a6ca4d3c8cec",
    "vendor_id": "a28ad32e-55b0-41ee-95e7-d83dda8eac2a",
    "vendor_name": "FireShield Technologies - V",
    "delivery_date": "2025-12-12",
    "items_delivered": "Protective Gear",
    "quantity": 87,
    "on_time_status": true,
    "quality_score": 4.49,
    "defect_count": 0,
    "issue_description": ""
  },
  {
    "delivery_id": "0896171d-5673-438a-93b5-0fd7d4e76fee",
    "vendor_id": "a27beb2d-c353-4be0-9a4c-477a3faa45b5",
    "vendor_name": "Guardian Safety Solutions - F",
    "delivery_date": "2025-07-24",
    "items_delivered": "Safety Helmets",
    "quantity": 460,
    "on_time_status": false,
    "quality_score": 4.11,
    "defect_count": 1,
    "issue_description": "Delayed delivery"
  },
  {
    "delivery_id": "e1922e1b-016d-4baf-8a3d-374d340e2432",
    "vendor_id": "05ec546b-598c-4435-8f5f-9e28000ac701",
    "vendor_name": "RapidResponse Suppliers - J",
    "delivery_date": "2025-11-06",
    "items_delivered": "Breathing Apparatus",
    "quantity": 413,
    "on_time_status": true,
    "quality_score": 4.54,
    "defect_count": 2,
    "issue_description": ""
  },
  {
    "delivery_id": "e61fbc52-0ee7-4dd6-8377-c2159c1c7676",
    "vendor_id": "34897448-66b2-431f-9c3e-b0cf10530c14",
    "vendor_name": "National Fire Services - S",
    "delivery_date": "2025-08-23",
    "items_delivered": "Fire Extinguishers",
    "quantity": 387,
    "on_time_status": true,
    "quality_score": 4.58,
    "defect_count": 0,
    "issue_description": ""
  },
  {
    "delivery_id": "d0bff89e-ea2f-4ff1-a511-418ac34416ee",
    "vendor_id": "882d6bad-c283-46b6-90f1-d473e25efdcd",
    "vendor_name": "Guardian Safety Solutions - O",
    "delivery_date": "2025-06-24",
    "items_delivered": "Communication Equipment",
    "quantity": 317,
    "on_time_status": true,
    "quality_score": 3.77,
    "defect_count": 2,
    "issue_description": "No issues"
  },
  {
    "delivery_id": "cb9b983e-45a8-4b1c-9adb-71158c095cdc",
    "vendor_id": "d8192924-6088-4421-9889-aafacfa3cb31",
    "vendor_name": "Blaze Control Systems - P",
    "delivery_date": "2025-03-02",
    "items_delivered": "Communication Equipment",
    "quantity": 93,
    "on_time_status": true,
    "quality_score": 4.57,
    "defect_count": 1,
    "issue_description": "Delayed delivery"
  },
  {
    "delivery_id": "7f97e60e-e53f-4cdc-93be-a627d18df277",
    "vendor_id": "d1abe418-5ef9-46e6-9b1b-9442198e9dff",
    "vendor_name": "National Fire Services - K",
    "delivery_date": "2025-12-12",
    "items_delivered": "Protective Gear",
    "quantity": 167,
    "on_time_status": true,
    "quality_score": 4.7,
    "defect_count": 0,
    "issue_description": ""
  },
  {
    "delivery_id": "e0f54042-6ce5-4636-8381-fecf02a9360f",
    "vendor_id": "916af05b-1000-4b91-868e-1582a65c8324",
    "vendor_name": "ProTech Safety Gear - M",
    "delivery_date": "2026-01-18",
    "items_delivered": "Protective Gear",
    "quantity": 432,
    "on_time_status": false,
    "quality_score": 4.86,
    "defect_count": 1,
    "issue_description": "Minor packaging damage"
  },
  {
    "delivery_id": "8e2486cb-6461-4d2f-8e4e-8c2178b6dc69",
    "vendor_id": "8dcdf82f-5127-47e4-9106-b207e5486bc5",
    "vendor_name": "SafeGuard Equipment Co - F",
    "delivery_date": "2025-09-18",
    "items_delivered": "Protective Gear",
    "quantity": 118,
    "on_time_status": true,
    "quality_score": 4.84,
    "defect_count": 2,
    "issue_description": ""
  },
  {
    "delivery_id": "bffa0f71-c6b5-4ff5-8998-1c715fe89064",
    "vendor_id": "bd6dd705-a44c-4009-91d9-20de59efd6c2",
    "vendor_name": "Alert Fire Protection - S",
    "delivery_date": "2025-10-30",
    "items_delivered": "Communication Equipment",
    "quantity": 88,
    "on_time_status": true,
    "quality_score": 4.37,
    "defect_count": 1,
    "issue_description": ""
  },
  {
    "delivery_id": "4f3b91a6-bd2a-468d-b1bf-b0edc2f7bd9a",
    "vendor_id": "1cf99934-8e1b-4468-ad91-ac9f7506b9f7",
    "vendor_name": "Emergency Response Solutions - W",
    "delivery_date": "2025-11-29",
    "items_delivered": "Communication Equipment",
    "quantity": 165,
    "on_time_status": false,
    "quality_score": 4.57,
    "defect_count": 4,
    "issue_description": "Documentation missing"
  },
  {
    "delivery_id": "793a9ce5-3b39-4899-9cd6-251cd0bacc24",
    "vendor_id": "a28ad32e-55b0-41ee-95e7-d83dda8eac2a",
    "vendor_name": "FireShield Technologies - V",
    "delivery_date": "2025-12-03",
    "items_delivered": "Safety Helmets",
    "quantity": 234,
    "on_time_status": true,
    "quality_score": 4.74,
    "defect_count": 2,
    "issue_description": ""
  },
  {
    "delivery_id": "75f9a43d-d24a-406d-82ed-f1d27758aee5",
    "vendor_id": "0fcdf246-8886-4e49-bda0-d801bf0e1281",
    "vendor_name": "Alert Fire Protection - G",
    "delivery_date": "2025-07-15",
    "items_delivered": "Protective Gear",
    "quantity": 471,
    "on_time_status": true,
    "quality_score": 3.85,
    "defect_count": 1,
    "issue_description": ""
  },
  {
    "delivery_id": "2ad35f55-654f-4c63-a8d9-f60c7e3a9e68",
    "vendor_id": "34897448-66b2-431f-9c3e-b0cf10530c14",
    "vendor_name": "National Fire Services - S",
    "delivery_date": "2025-03-02",
    "items_delivered": "Fire Hoses",
    "quantity": 63,
    "on_time_status": true,
    "quality_score": 4.09,
    "defect_count": 0,
    "issue_description": ""
  },
  {
    "delivery_id": "32dc78c6-148f-49af-b2ce-970a5c9550a4",
    "vendor_id": "b4dd8826-1cf6-4af2-b0e0-d14b25f01eec",
    "vendor_name": "Alert Fire Protection - Q",
    "delivery_date": "2025-02-10",
    "items_delivered": "Fire Extinguishers",
    "quantity": 283,
    "on_time_status": true,
    "quality_score": 3.8,
    "defect_count": 0,
    "issue_description": "Quality issues"
  },
  {
    "delivery_id": "ba09b554-0aaf-4ffc-aa43-f1b01343be8d",
    "vendor_id": "916af05b-1000-4b91-868e-1582a65c8324",
    "vendor_name": "ProTech Safety Gear - M",
    "delivery_date": "2025-02-06",
    "items_delivered": "Communication Equipment",
    "quantity": 14,
    "on_time_status": true,
    "quality_score": 4.51,
    "defect_count": 2,
    "issue_description": "No issues"
  },
  {
    "delivery_id": "6c26d7d2-d044-4b25-9427-b891552e3d94",
    "vendor_id": "ee54677b-a315-4170-9a1b-eb8ff0b6dff0",
    "vendor_name": "Blaze Control Systems - E",
    "delivery_date": "2025-11-20",
    "items_delivered": "Fire Extinguishers",
    "quantity": 147,
    "on_time_status": true,
    "quality_score": 3.53,
    "defect_count": 2,
    "issue_description": "Minor packaging damage"
  },
  {
    "delivery_id": "d228a1ff-3624-46c5-9232-c2066f3cf723",
    "vendor_id": "d8192924-6088-4421-9889-aafacfa3cb31",
    "vendor_name": "Blaze Control Systems - P",
    "delivery_date": "2025-01-31",
    "items_delivered": "Safety Helmets",
    "quantity": 42,
    "on_time_status": true,
    "quality_score": 4.25,
    "defect_count": 2,
    "issue_description": ""
  },
  {
    "delivery_id": "0e788322-0735-43da-933c-3868a5d8e74b",
    "vendor_id": "ed7eee20-a6ca-4ee8-b54a-452eac70c056",
    "vendor_name": "National Fire Services - H",
    "delivery_date": "2025-05-02",
    "items_delivered": "Fire Hoses",
    "quantity": 248,
    "on_time_status": true,
    "quality_score": 3.57,
    "defect_count": 2,
    "issue_description": ""
  },
  {
    "delivery_id": "dd29d537-bbd3-4576-97a5-54ead54f82e6",
    "vendor_id": "1cf99934-8e1b-4468-ad91-ac9f7506b9f7",
    "vendor_name": "Emergency Response Solutions - W",
    "delivery_date": "2025-03-20",
    "items_delivered": "Breathing Apparatus",
    "quantity": 262,
    "on_time_status": false,
    "quality_score": 4.73,
    "defect_count": 2,
    "issue_description": "Incomplete order"
  },
  {
    "delivery_id": "f641c1dd-cd2f-419b-90ea-b6ed27b37c17",
    "vendor_id": "05ec546b-598c-4435-8f5f-9e28000ac701",
    "vendor_name": "RapidResponse Suppliers - J",
    "delivery_date": "2025-08-07",
    "items_delivered": "Protective Gear",
    "quantity": 310,
    "on_time_status": true,
    "quality_score": 3.5,
    "defect_count": 1,
    "issue_description": "Minor packaging damage"
  },
  {
    "delivery_id": "d90359d5-d28f-4d55-a9b7-4631cc9613c5",
    "vendor_id": "29aa9588-6658-4615-b904-23ca2df08575",
    "vendor_name": "Guardian Safety Solutions - E",
    "delivery_date": "2025-05-13",
    "items_delivered": "Protective Gear",
    "quantity": 493,
    "on_time_status": false,
    "quality_score": 4.46,
    "defect_count": 5,
    "issue_description": "Documentation missing"
  },
  {
    "delivery_id": "ad304f94-be39-4c52-becc-795522504321",
    "vendor_id": "d8192924-6088-4421-9889-aafacfa3cb31",
    "vendor_name": "Blaze Control Systems - P",
    "delivery_date": "2025-12-06",
    "items_delivered": "Fire Hoses",
    "quantity": 150,
    "on_time_status": true,
    "quality_score": 4.15,
    "defect_count": 1,
    "issue_description": ""
  },
  {
    "delivery_id": "10fbecbb-b8ad-4e19-a95b-f33a0a0d7515",
    "vendor_id": "9f95005e-ad9e-473e-83a9-602256353a95",
    "vendor_name": "Advanced Safety Equipment - N",
    "delivery_date": "2025-06-12",
    "items_delivered": "Safety Helmets",
    "quantity": 181,
    "on_time_status": true,
    "quality_score": 3.84,
    "defect_count": 1,
    "issue_description": ""
  },
  {
    "delivery_id": "6e2bd15a-e59c-446b-8b1b-bfa81ae7f3cf",
    "vendor_id": "8fe0cc12-6d82-41bb-9fa0-422dd9c8d13c",
    "vendor_name": "FireSafe India Pvt Ltd - K",
    "delivery_date": "2026-01-03",
    "items_delivered": "Fire Extinguishers",
    "quantity": 198,
    "on_time_status": true,
    "quality_score": 4.78,
    "defect_count": 1,
    "issue_description": ""
  },
  {
    "delivery_id": "c88610f3-cf2b-43d1-99ab-d7955f35a330",
    "vendor_id": "d9a9634b-ebe9-42b4-9254-2e7a37916db5",
    "vendor_name": "ProTech Safety Gear - R",
    "delivery_date": "2026-01-18",
    "items_delivered": "Communication Equipment",
    "quantity": 72,
    "on_time_status": true,
    "quality_score": 3.51,
    "defect_count": 1,
    "issue_description": ""
  },
  {
    "delivery_id": "5c46b290-a2a8-44f7-90af-a8c4bd98768f",
    "vendor_id": "05ec546b-598c-4435-8f5f-9e28000ac701",
    "vendor_name": "RapidResponse Suppliers - J",
    "delivery_date": "2025-11-13",
    "items_delivered": "Protective Gear",
    "quantity": 45,
    "on_time_status": true,
    "quality_score": 3.51,
    "defect_count": 2,
    "issue_description": ""
  },
  {
    "delivery_id": "e4706f52-870d-4c23-934b-4fe6b270d09f",
    "vendor_id": "72ef11ee-138b-42da-9031-ff79e7425bb1",
    "vendor_name": "Guardian Safety Solutions - I",
    "delivery_date": "2026-01-04",
    "items_delivered": "Protective Gear",
    "quantity": 443,
    "on_time_status": true,
    "quality_score": 3.73,
    "defect_count": 2,
    "issue_description": ""
  },
  {
    "delivery_id": "4c74db6e-5e6e-4d95-b460-730a7930e361",
    "vendor_id": "916af05b-1000-4b91-868e-1582a65c8324",
    "vendor_name": "ProTech Safety Gear - M",
    "delivery_date": "2025-02-27",
    "items_delivered": "Fire Extinguishers",
    "quantity": 436,
    "on_time_status": true,
    "quality_score": 4.78,
    "defect_count": 0,
    "issue_description": "No issues"
  },
  {
    "delivery_id": "ff2e6707-fecf-4847-8eba-a2134929ea81",
    "vendor_id": "e6d913ac-e1c0-4924-816b-caeb155a96a9",
    "vendor_name": "FireShield Technologies - T",
    "delivery_date": "2025-11-02",
    "items_delivered": "Breathing Apparatus",
    "quantity": 349,
    "on_time_status": true,
    "quality_score": 3.65,
    "defect_count": 0,
    "issue_description": ""
  },
  {
    "delivery_id": "7c568ff2-c169-49e2-aa96-593499c88366",
    "vendor_id": "916af05b-1000-4b91-868e-1582a65c8324",
    "vendor_name": "ProTech Safety Gear - M",
    "delivery_date": "2025-11-01",
    "items_delivered": "Fire Hoses",
    "quantity": 412,
    "on_time_status": true,
    "quality_score": 4.51,
    "defect_count": 2,
    "issue_description": ""
  },
  {
    "delivery_id": "2acb3943-91ad-4ef4-bcc9-74b4ef59b9b1",
    "vendor_id": "8023d5ed-e138-4114-9b33-5b078e94c4aa",
    "vendor_name": "SecureLife Fire Systems - C",
    "delivery_date": "2025-02-20",
    "items_delivered": "Communication Equipment",
    "quantity": 444,
    "on_time_status": true,
    "quality_score": 4.54,
    "defect_count": 1,
    "issue_description": ""
  },
  {
    "delivery_id": "f37c339a-049e-4086-a5be-608e70d9e2ae",
    "vendor_id": "1660174a-e73a-4504-bcfa-aec7cd48726d",
    "vendor_name": "Guardian Safety Solutions - D",
    "delivery_date": "2025-12-14",
    "items_delivered": "Protective Gear",
    "quantity": 119,
    "on_time_status": false,
    "quality_score": 4.38,
    "defect_count": 3,
    "issue_description": "No issues"
  },
  {
    "delivery_id": "8577f2bf-55ce-4ed2-899d-bdc5f35edb7b",
    "vendor_id": "f6a95519-0601-4e89-912d-a94ad74baba5",
    "vendor_name": "National Fire Services - G",
    "delivery_date": "2025-02-26",
    "items_delivered": "Fire Extinguishers",
    "quantity": 171,
    "on_time_status": true,
    "quality_score": 4.41,
    "defect_count": 0,
    "issue_description": ""
  },
  {
    "delivery_id": "ba91d7a2-002a-499b-a3fa-1b89b94ff502",
    "vendor_id": "1cf99934-8e1b-4468-ad91-ac9f7506b9f7",
    "vendor_name": "Emergency Response Solutions - W",
    "delivery_date": "2025-05-24",
    "items_delivered": "Fire Hoses",
    "quantity": 463,
    "on_time_status": true,
    "quality_score": 4.29,
    "defect_count": 0,
    "issue_description": ""
  },
  {
    "delivery_id": "6b562a5c-b65c-4fc3-90f7-86f06db1cfc0",
    "vendor_id": "8dcdf82f-5127-47e4-9106-b207e5486bc5",
    "vendor_name": "SafeGuard Equipment Co - F",
    "delivery_date": "2025-09-04",
    "items_delivered": "Breathing Apparatus",
    "quantity": 429,
    "on_time_status": true,
    "quality_score": 4.7,
    "defect_count": 0,
    "issue_description": ""
  },
  {
    "delivery_id": "7d16c7e2-6bd4-4cda-95af-6859b6039fb4",
    "vendor_id": "ee54677b-a315-4170-9a1b-eb8ff0b6dff0",
    "vendor_name": "Blaze Control Systems - E",
    "delivery_date": "2025-09-21",
    "items_delivered": "Breathing Apparatus",
    "quantity": 24,
    "on_time_status": true,
    "quality_score": 4.05,
    "defect_count": 0,
    "issue_description": ""
  },
  {
    "delivery_id": "60247828-90df-40e8-bccb-067e9f3bf27f",
    "vendor_id": "a27beb2d-c353-4be0-9a4c-477a3faa45b5",
    "vendor_name": "Guardian Safety Solutions - F",
    "delivery_date": "2025-12-25",
    "items_delivered": "Breathing Apparatus",
    "quantity": 151,
    "on_time_status": true,
    "quality_score": 4.91,
    "defect_count": 2,
    "issue_description": ""
  },
  {
    "delivery_id": "12b6b6ff-688d-4769-86df-d975ef0a456b",
    "vendor_id": "cf6ccc2a-ef39-4df3-8610-cb7e9cda5773",
    "vendor_name": "Guardian Safety Solutions - I",
    "delivery_date": "2025-08-07",
    "items_delivered": "Communication Equipment",
    "quantity": 228,
    "on_time_status": true,
    "quality_score": 4.66,
    "defect_count": 2,
    "issue_description": ""
  },
  {
    "delivery_id": "626722f7-0ee4-455a-912a-c3bbe645bc57",
    "vendor_id": "a16c821a-6baf-4910-a107-fa60bd06c870",
    "vendor_name": "Blaze Control Systems - V",
    "delivery_date": "2025-12-28",
    "items_delivered": "Communication Equipment",
    "quantity": 92,
    "on_time_status": true,
    "quality_score": 3.77,
    "defect_count": 2,
    "issue_description": "Minor packaging damage"
  },
  {
    "delivery_id": "9760289c-52ca-485b-875d-4e3d484f670e",
    "vendor_id": "1cf99934-8e1b-4468-ad91-ac9f7506b9f7",
    "vendor_name": "Emergency Response Solutions - W",
    "delivery_date": "2025-05-09",
    "items_delivered": "Communication Equipment",
    "quantity": 403,
    "on_time_status": true,
    "quality_score": 4.5,
    "defect_count": 1,
    "issue_description": ""
  },
  {
    "delivery_id": "99b1bee7-1e81-4347-ac4c-147d148b2407",
    "vendor_id": "fa658a7b-1f0a-4fec-a36d-c270b8ac2e88",
    "vendor_name": "Advanced Safety Equipment - L",
    "delivery_date": "2025-02-08",
    "items_delivered": "Fire Extinguishers",
    "quantity": 423,
    "on_time_status": true,
    "quality_score": 3.57,
    "defect_count": 1,
    "issue_description": ""
  },
  {
    "delivery_id": "19d27953-f66f-4254-9d14-5ea066c78abb",
    "vendor_id": "4ad1efb1-1e75-405a-b32d-370fd7d83754",
    "vendor_name": "Blaze Control Systems - R",
    "delivery_date": "2025-04-16",
    "items_delivered": "Fire Hoses",
    "quantity": 236,
    "on_time_status": true,
    "quality_score": 4.56,
    "defect_count": 2,
    "issue_description": ""
  },
  {
    "delivery_id": "d832af56-904b-403f-97ef-680ea394ae7d",
    "vendor_id": "a28ad32e-55b0-41ee-95e7-d83dda8eac2a",
    "vendor_name": "FireShield Technologies - V",
    "delivery_date": "2025-11-30",
    "items_delivered": "Fire Extinguishers",
    "quantity": 239,
    "on_time_status": false,
    "quality_score": 4.31,
    "defect_count": 4,
    "issue_description": "Quality issues"
  },
  {
    "delivery_id": "79581ea2-12f4-4ef1-a8fa-0e7d89c771d9",
    "vendor_id": "0fcdf246-8886-4e49-bda0-d801bf0e1281",
    "vendor_name": "Alert Fire Protection - G",
    "delivery_date": "2025-11-25",
    "items_delivered": "Fire Hoses",
    "quantity": 299,
    "on_time_status": true,
    "quality_score": 4.56,
    "defect_count": 1,
    "issue_description": ""
  },
  {
    "delivery_id": "b0f19d7b-4d8b-4724-b0f1-3cc83981b6f7",
    "vendor_id": "8fe0cc12-6d82-41bb-9fa0-422dd9c8d13c",
    "vendor_name": "FireSafe India Pvt Ltd - K",
    "delivery_date": "2025-06-17",
    "items_delivered": "Fire Extinguishers",
    "quantity": 441,
    "on_time_status": true,
    "quality_score": 3.51,
    "defect_count": 2,
    "issue_description": ""
  },
  {
    "delivery_id": "5b3d9e56-5216-4f17-b809-d358c598095d",
    "vendor_id": "44f3f137-6d1a-4e85-a467-b9c4e668d880",
    "vendor_name": "Advanced Safety Equipment - T",
    "delivery_date": "2025-02-25",
    "items_delivered": "Communication Equipment",
    "quantity": 371,
    "on_time_status": true,
    "quality_score": 4.7,
    "defect_count": 1,
    "issue_description": ""
  },
  {
    "delivery_id": "70c0d310-ca65-441d-bff8-a111540cb3a7",
    "vendor_id": "0ee45aad-7218-4fbd-a019-7808cf810307",
    "vendor_name": "SecureLife Fire Systems - Y",
    "delivery_date": "2025-07-23",
    "items_delivered": "Breathing Apparatus",
    "quantity": 187,
    "on_time_status": true,
    "quality_score": 4.14,
    "defect_count": 1,
    "issue_description": ""
  },
  {
    "delivery_id": "8dc2f348-9506-4d11-a410-b19bb02310f2",
    "vendor_id": "8023d5ed-e138-4114-9b33-5b078e94c4aa",
    "vendor_name": "SecureLife Fire Systems - C",
    "delivery_date": "2025-07-06",
    "items_delivered": "Safety Helmets",
    "quantity": 362,
    "on_time_status": true,
    "quality_score": 4.96,
    "defect_count": 0,
    "issue_description": ""
  },
  {
    "delivery_id": "11c6798b-abeb-48c7-bf1d-d69bc9b61aa2",
    "vendor_id": "44f3f137-6d1a-4e85-a467-b9c4e668d880",
    "vendor_name": "Advanced Safety Equipment - T",
    "delivery_date": "2025-10-26",
    "items_delivered": "Protective Gear",
    "quantity": 472,
    "on_time_status": true,
    "quality_score": 3.55,
    "defect_count": 2,
    "issue_description": ""
  },
  {
    "delivery_id": "c09e3769-e93c-4336-81a0-4df27690379c",
    "vendor_id": "4ad1efb1-1e75-405a-b32d-370fd7d83754",
    "vendor_name": "Blaze Control Systems - R",
    "delivery_date": "2025-01-27",
    "items_delivered": "Fire Hoses",
    "quantity": 132,
    "on_time_status": true,
    "quality_score": 3.91,
    "defect_count": 0,
    "issue_description": ""
  },
  {
    "delivery_id": "080fe195-87b6-42d7-bf13-9a3d6f02f4a6",
    "vendor_id": "b1e4a21b-f759-4457-ae30-18db2fc6fe94",
    "vendor_name": "National Fire Services - U",
    "delivery_date": "2025-02-02",
    "items_delivered": "Safety Helmets",
    "quantity": 173,
    "on_time_status": true,
    "quality_score": 4.72,
    "defect_count": 1,
    "issue_description": ""
  },
  {
    "delivery_id": "a63afeb7-e290-4ee2-9a89-192b6d8789db",
    "vendor_id": "967e8f3a-c333-49fa-a2d1-b7563692d43d",
    "vendor_name": "Alert Fire Protection - M",
    "delivery_date": "2025-10-30",
    "items_delivered": "Protective Gear",
    "quantity": 297,
    "on_time_status": true,
    "quality_score": 4.2,
    "defect_count": 0,
    "issue_description": ""
  },
  {
    "delivery_id": "ff44ce88-47f4-437e-962f-1be2ac2a41cd",
    "vendor_id": "4ee2786a-2917-4a1f-92ec-976e27cf8a2d",
    "vendor_name": "FireSafe India Pvt Ltd - L",
    "delivery_date": "2025-07-07",
    "items_delivered": "Breathing Apparatus",
    "quantity": 52,
    "on_time_status": true,
    "quality_score": 3.68,
    "defect_count": 0,
    "issue_description": ""
  },
  {
    "delivery_id": "4d512a06-b2dd-48ee-a9b6-5fedcdca1fb7",
    "vendor_id": "757511b3-18d6-46e9-8886-eddc26824fca",
    "vendor_name": "ProTech Safety Gear - W",
    "delivery_date": "2025-07-26",
    "items_delivered": "Safety Helmets",
    "quantity": 273,
    "on_time_status": false,
    "quality_score": 4.21,
    "defect_count": 0,
    "issue_description": "Incomplete order"
  },
  {
    "delivery_id": "b79f5585-52e8-495f-9198-b828f0fda6dc",
    "vendor_id": "1660174a-e73a-4504-bcfa-aec7cd48726d",
    "vendor_name": "Guardian Safety Solutions - D",
    "delivery_date": "2025-10-16",
    "items_delivered": "Breathing Apparatus",
    "quantity": 328,
    "on_time_status": true,
    "quality_score": 3.7,
    "defect_count": 0,
    "issue_description": ""
  },
  {
    "delivery_id": "b0127e83-8867-4bb0-9578-e7571cf8d717",
    "vendor_id": "8d93fcaa-b572-43a9-9c47-05acf2e14ffc",
    "vendor_name": "FireSafe India Pvt Ltd - H",
    "delivery_date": "2025-02-12",
    "items_delivered": "Communication Equipment",
    "quantity": 272,
    "on_time_status": false,
    "quality_score": 4.44,
    "defect_count": 1,
    "issue_description": "Incomplete order"
  },
  {
    "delivery_id": "eb135d42-d881-4b7a-a92a-5c89b3b0b178",
    "vendor_id": "d1abe418-5ef9-46e6-9b1b-9442198e9dff",
    "vendor_name": "National Fire Services - K",
    "delivery_date": "2025-10-17",
    "items_delivered": "Fire Extinguishers",
    "quantity": 431,
    "on_time_status": true,
    "quality_score": 4.44,
    "defect_count": 0,
    "issue_description": ""
  },
  {
    "delivery_id": "2b44892c-77aa-48a7-b3bc-b56d381d88fe",
    "vendor_id": "aff23462-f0db-4391-9713-552269e81c5f",
    "vendor_name": "SecureLife Fire Systems - O",
    "delivery_date": "2025-05-12",
    "items_delivered": "Protective Gear",
    "quantity": 18,
    "on_time_status": true,
    "quality_score": 4.1,
    "defect_count": 2,
    "issue_description": ""
  },
  {
    "delivery_id": "afc336a0-9142-4424-9f0f-871c40964357",
    "vendor_id": "bd6dd705-a44c-4009-91d9-20de59efd6c2",
    "vendor_name": "Alert Fire Protection - S",
    "delivery_date": "2025-08-29",
    "items_delivered": "Communication Equipment",
    "quantity": 455,
    "on_time_status": false,
    "quality_score": 3.64,
    "defect_count": 2,
    "issue_description": "Minor packaging damage"
  },
  {
    "delivery_id": "02e87d70-af09-4f7a-86fe-8da1aad18762",
    "vendor_id": "8d93fcaa-b572-43a9-9c47-05acf2e14ffc",
    "vendor_name": "FireSafe India Pvt Ltd - H",
    "delivery_date": "2025-09-20",
    "items_delivered": "Breathing Apparatus",
    "quantity": 128,
    "on_time_status": false,
    "quality_score": 3.58,
    "defect_count": 1,
    "issue_description": "Quality issues"
  },
  {
    "delivery_id": "50982683-7958-48c7-b49a-ada4fe3a6f98",
    "vendor_id": "b4dd8826-1cf6-4af2-b0e0-d14b25f01eec",
    "vendor_name": "Alert Fire Protection - Q",
    "delivery_date": "2025-02-01",
    "items_delivered": "Communication Equipment",
    "quantity": 227,
    "on_time_status": true,
    "quality_score": 4.66,
    "defect_count": 1,
    "issue_description": ""
  },
  {
    "delivery_id": "ec9a88ba-976f-41f4-a825-1bfbd1bda30b",
    "vendor_id": "916af05b-1000-4b91-868e-1582a65c8324",
    "vendor_name": "ProTech Safety Gear - M",
    "delivery_date": "2025-08-18",
    "items_delivered": "Fire Extinguishers",
    "quantity": 264,
    "on_time_status": false,
    "quality_score": 3.93,
    "defect_count": 1,
    "issue_description": "Quality issues"
  },
  {
    "delivery_id": "aa7197fb-d37c-41e4-87b5-06aaea5762c5",
    "vendor_id": "882d6bad-c283-46b6-90f1-d473e25efdcd",
    "vendor_name": "Guardian Safety Solutions - O",
    "delivery_date": "2025-05-13",
    "items_delivered": "Safety Helmets",
    "quantity": 276,
    "on_time_status": true,
    "quality_score": 4.82,
    "defect_count": 0,
    "issue_description": ""
  },
  {
    "delivery_id": "5be9515d-d35a-4af3-aadf-bcfa3b18b2e0",
    "vendor_id": "e6d913ac-e1c0-4924-816b-caeb155a96a9",
    "vendor_name": "FireShield Technologies - T",
    "delivery_date": "2025-04-11",
    "items_delivered": "Fire Extinguishers",
    "quantity": 355,
    "on_time_status": true,
    "quality_score": 3.99,
    "defect_count": 2,
    "issue_description": ""
  },
  {
    "delivery_id": "991b6160-9d46-41cb-936c-c5d68b4c477c",
    "vendor_id": "b1e4a21b-f759-4457-ae30-18db2fc6fe94",
    "vendor_name": "National Fire Services - U",
    "delivery_date": "2025-09-25",
    "items_delivered": "Fire Extinguishers",
    "quantity": 215,
    "on_time_status": true,
    "quality_score": 4.42,
    "defect_count": 2,
    "issue_description": ""
  },
  {
    "delivery_id": "3c1e6d7e-9c3f-4533-b05f-ac5030213655",
    "vendor_id": "9f95005e-ad9e-473e-83a9-602256353a95",
    "vendor_name": "Advanced Safety Equipment - N",
    "delivery_date": "2025-07-22",
    "items_delivered": "Breathing Apparatus",
    "quantity": 12,
    "on_time_status": true,
    "quality_score": 3.57,
    "defect_count": 2,
    "issue_description": "Quality issues"
  },
  {
    "delivery_id": "1cc61a24-a897-43a4-98bd-405beec6c114",
    "vendor_id": "8d93fcaa-b572-43a9-9c47-05acf2e14ffc",
    "vendor_name": "FireSafe India Pvt Ltd - H",
    "delivery_date": "2025-10-29",
    "items_delivered": "Fire Hoses",
    "quantity": 398,
    "on_time_status": false,
    "quality_score": 3.95,
    "defect_count": 4,
    "issue_description": "Delayed delivery"
  },
  {
    "delivery_id": "b56f9a9d-5f63-4367-82a4-7253bd9d1555",
    "vendor_id": "d8192924-6088-4421-9889-aafacfa3cb31",
    "vendor_name": "Blaze Control Systems - P",
    "delivery_date": "2025-12-02",
    "items_delivered": "Fire Extinguishers",
    "quantity": 296,
    "on_time_status": true,
    "quality_score": 4.01,
    "defect_count": 0,
    "issue_description": ""
  },
  {
    "delivery_id": "45a8f43e-1b25-4022-9b04-094e8cf0ac89",
    "vendor_id": "f6a95519-0601-4e89-912d-a94ad74baba5",
    "vendor_name": "National Fire Services - G",
    "delivery_date": "2025-09-27",
    "items_delivered": "Safety Helmets",
    "quantity": 149,
    "on_time_status": true,
    "quality_score": 3.94,
    "defect_count": 2,
    "issue_description": ""
  },
  {
    "delivery_id": "bd4e3d94-683e-42f0-973f-bad7b39c74ae",
    "vendor_id": "f96ed92f-cac6-42b9-816e-583ba91a77ec",
    "vendor_name": "ProTech Safety Gear - Q",
    "delivery_date": "2025-10-23",
    "items_delivered": "Safety Helmets",
    "quantity": 160,
    "on_time_status": false,
    "quality_score": 4.76,
    "defect_count": 0,
    "issue_description": "Delayed delivery"
  },
  {
    "delivery_id": "66e193c3-e810-404a-b504-fde33bfbfc1c",
    "vendor_id": "6363e847-65c4-4134-b749-09a54e35ef4e",
    "vendor_name": "ProTech Safety Gear - B",
    "delivery_date": "2025-09-22",
    "items_delivered": "Fire Extinguishers",
    "quantity": 500,
    "on_time_status": false,
    "quality_score": 3.7,
    "defect_count": 2,
    "issue_description": "No issues"
  },
  {
    "delivery_id": "220f0447-4251-4c3e-843b-985d06c69be1",
    "vendor_id": "aff23462-f0db-4391-9713-552269e81c5f",
    "vendor_name": "SecureLife Fire Systems - O",
    "delivery_date": "2025-12-02",
    "items_delivered": "Safety Helmets",
    "quantity": 226,
    "on_time_status": false,
    "quality_score": 4.33,
    "defect_count": 3,
    "issue_description": "No issues"
  },
  {
    "delivery_id": "5dda3c75-dd8a-453d-b104-3434e68a03d1",
    "vendor_id": "a28ad32e-55b0-41ee-95e7-d83dda8eac2a",
    "vendor_name": "FireShield Technologies - V",
    "delivery_date": "2025-10-31",
    "items_delivered": "Protective Gear",
    "quantity": 266,
    "on_time_status": true,
    "quality_score": 4.13,
    "defect_count": 1,
    "issue_description": "Delayed delivery"
  },
  {
    "delivery_id": "7f901c57-4cab-4f67-b7a1-f0067fabe41b",
    "vendor_id": "1660174a-e73a-4504-bcfa-aec7cd48726d",
    "vendor_name": "Guardian Safety Solutions - D",
    "delivery_date": "2025-06-20",
    "items_delivered": "Breathing Apparatus",
    "quantity": 146,
    "on_time_status": true,
    "quality_score": 3.68,
    "defect_count": 0,
    "issue_description": ""
  },
  {
    "delivery_id": "0e636710-89ad-4d84-8cdb-2afa011e6f9f",
    "vendor_id": "fa658a7b-1f0a-4fec-a36d-c270b8ac2e88",
    "vendor_name": "Advanced Safety Equipment - L",
    "delivery_date": "2025-04-24",
    "items_delivered": "Fire Extinguishers",
    "quantity": 368,
    "on_time_status": true,
    "quality_score": 3.96,
    "defect_count": 0,
    "issue_description": ""
  },
  {
    "delivery_id": "985de416-8288-4104-81e6-8544996ae98f",
    "vendor_id": "a28ad32e-55b0-41ee-95e7-d83dda8eac2a",
    "vendor_name": "FireShield Technologies - V",
    "delivery_date": "2025-06-26",
    "items_delivered": "Safety Helmets",
    "quantity": 53,
    "on_time_status": true,
    "quality_score": 4.84,
    "defect_count": 1,
    "issue_description": ""
  },
  {
    "delivery_id": "2fb903e1-03c1-4169-a6a6-b114215c5134",
    "vendor_id": "4ee2786a-2917-4a1f-92ec-976e27cf8a2d",
    "vendor_name": "FireSafe India Pvt Ltd - L",
    "delivery_date": "2025-07-05",
    "items_delivered": "Fire Extinguishers",
    "quantity": 132,
    "on_time_status": true,
    "quality_score": 3.9,
    "defect_count": 0,
    "issue_description": ""
  },
  {
    "delivery_id": "9a515edb-68e1-4b6f-a9cf-8200b44d3abe",
    "vendor_id": "757511b3-18d6-46e9-8886-eddc26824fca",
    "vendor_name": "ProTech Safety Gear - W",
    "delivery_date": "2025-07-30",
    "items_delivered": "Protective Gear",
    "quantity": 146,
    "on_time_status": true,
    "quality_score": 4.23,
    "defect_count": 1,
    "issue_description": ""
  },
  {
    "delivery_id": "ed03380f-3f54-487f-a7cb-9441c65b69e3",
    "vendor_id": "7a522c24-b040-4be9-a9be-ac1b92af655a",
    "vendor_name": "Blaze Control Systems - C",
    "delivery_date": "2025-05-19",
    "items_delivered": "Safety Helmets",
    "quantity": 92,
    "on_time_status": false,
    "quality_score": 4.92,
    "defect_count": 4,
    "issue_description": "Minor packaging damage"
  },
  {
    "delivery_id": "2bdbfbdc-f003-44e4-8a1a-98d5c4a34c5f",
    "vendor_id": "8fe0cc12-6d82-41bb-9fa0-422dd9c8d13c",
    "vendor_name": "FireSafe India Pvt Ltd - K",
    "delivery_date": "2025-03-07",
    "items_delivered": "Fire Hoses",
    "quantity": 475,
    "on_time_status": true,
    "quality_score": 3.72,
    "defect_count": 0,
    "issue_description": ""
  },
  {
    "delivery_id": "f74f31fa-ddab-4719-b652-9a36a60dc9bb",
    "vendor_id": "f6a95519-0601-4e89-912d-a94ad74baba5",
    "vendor_name": "National Fire Services - G",
    "delivery_date": "2025-06-18",
    "items_delivered": "Breathing Apparatus",
    "quantity": 232,
    "on_time_status": false,
    "quality_score": 4.3,
    "defect_count": 0,
    "issue_description": "Quality issues"
  },
  {
    "delivery_id": "a876bb32-d8ec-4c09-b9d8-e408e16e25f8",
    "vendor_id": "882d6bad-c283-46b6-90f1-d473e25efdcd",
    "vendor_name": "Guardian Safety Solutions - O",
    "delivery_date": "2025-12-28",
    "items_delivered": "Communication Equipment",
    "quantity": 283,
    "on_time_status": true,
    "quality_score": 4.76,
    "defect_count": 0,
    "issue_description": ""
  },
  {
    "delivery_id": "1e782369-b37b-43df-a299-19d1f4898789",
    "vendor_id": "bd6dd705-a44c-4009-91d9-20de59efd6c2",
    "vendor_name": "Alert Fire Protection - S",
    "delivery_date": "2025-08-17",
    "items_delivered": "Breathing Apparatus",
    "quantity": 463,
    "on_time_status": true,
    "quality_score": 4.59,
    "defect_count": 2,
    "issue_description": "Documentation missing"
  },
  {
    "delivery_id": "7ad3cd18-ec7a-42ae-9a0d-40abb44824ca",
    "vendor_id": "5ee342c3-ad83-45ea-8de4-b9b4e9729227",
    "vendor_name": "RapidResponse Suppliers - X",
    "delivery_date": "2025-02-23",
    "items_delivered": "Communication Equipment",
    "quantity": 210,
    "on_time_status": true,
    "quality_score": 3.82,
    "defect_count": 1,
    "issue_description": ""
  },
  {
    "delivery_id": "22003654-32e9-411a-a1cf-24521a2fdd5e",
    "vendor_id": "fb0f4a3c-054d-406f-9a53-fd19d31957c1",
    "vendor_name": "SecureLife Fire Systems - N",
    "delivery_date": "2025-12-09",
    "items_delivered": "Safety Helmets",
    "quantity": 468,
    "on_time_status": true,
    "quality_score": 4.39,
    "defect_count": 1,
    "issue_description": ""
  },
  {
    "delivery_id": "d7be3f3d-5302-4ef8-a003-c61801dd568a",
    "vendor_id": "916af05b-1000-4b91-868e-1582a65c8324",
    "vendor_name": "ProTech Safety Gear - M",
    "delivery_date": "2025-02-15",
    "items_delivered": "Safety Helmets",
    "quantity": 423,
    "on_time_status": true,
    "quality_score": 4.67,
    "defect_count": 2,
    "issue_description": ""
  },
  {
    "delivery_id": "22dbe1d4-3988-4203-b537-79c4c437f18b",
    "vendor_id": "9ca723b9-570c-4a06-91fa-34a7298caff8",
    "vendor_name": "FireSafe India Pvt Ltd - P",
    "delivery_date": "2025-04-05",
    "items_delivered": "Communication Equipment",
    "quantity": 308,
    "on_time_status": true,
    "quality_score": 3.96,
    "defect_count": 2,
    "issue_description": ""
  },
  {
    "delivery_id": "8644e33e-9a1c-459d-bd2b-439be90cb86e",
    "vendor_id": "a16c821a-6baf-4910-a107-fa60bd06c870",
    "vendor_name": "Blaze Control Systems - V",
    "delivery_date": "2025-11-08",
    "items_delivered": "Fire Extinguishers",
    "quantity": 13,
    "on_time_status": true,
    "quality_score": 4.88,
    "defect_count": 0,
    "issue_description": ""
  },
  {
    "delivery_id": "80508268-eff0-42e4-a086-8c3b138cb1ec",
    "vendor_id": "1cf99934-8e1b-4468-ad91-ac9f7506b9f7",
    "vendor_name": "Emergency Response Solutions - W",
    "delivery_date": "2025-12-20",
    "items_delivered": "Breathing Apparatus",
    "quantity": 378,
    "on_time_status": false,
    "quality_score": 4.2,
    "defect_count": 0,
    "issue_description": "Incomplete order"
  },
  {
    "delivery_id": "330f1dc4-f509-4c0e-a520-660ad5c8a675",
    "vendor_id": "a27beb2d-c353-4be0-9a4c-477a3faa45b5",
    "vendor_name": "Guardian Safety Solutions - F",
    "delivery_date": "2025-04-04",
    "items_delivered": "Breathing Apparatus",
    "quantity": 125,
    "on_time_status": true,
    "quality_score": 3.54,
    "defect_count": 2,
    "issue_description": ""
  },
  {
    "delivery_id": "45b43ded-104a-411f-b899-4ab53767cbdb",
    "vendor_id": "1660174a-e73a-4504-bcfa-aec7cd48726d",
    "vendor_name": "Guardian Safety Solutions - D",
    "delivery_date": "2025-03-12",
    "items_delivered": "Fire Hoses",
    "quantity": 96,
    "on_time_status": true,
    "quality_score": 4.3,
    "defect_count": 2,
    "issue_description": ""
  },
  {
    "delivery_id": "7e11dbd3-b2f2-418b-b221-97c322328bb0",
    "vendor_id": "44f3f137-6d1a-4e85-a467-b9c4e668d880",
    "vendor_name": "Advanced Safety Equipment - T",
    "delivery_date": "2026-01-23",
    "items_delivered": "Safety Helmets",
    "quantity": 56,
    "on_time_status": true,
    "quality_score": 3.55,
    "defect_count": 2,
    "issue_description": ""
  },
  {
    "delivery_id": "126cafe1-c23b-4c4e-9c90-aead9c79846c",
    "vendor_id": "9f95005e-ad9e-473e-83a9-602256353a95",
    "vendor_name": "Advanced Safety Equipment - N",
    "delivery_date": "2025-09-20",
    "items_delivered": "Safety Helmets",
    "quantity": 369,
    "on_time_status": false,
    "quality_score": 3.59,
    "defect_count": 4,
    "issue_description": "Incomplete order"
  },
  {
    "delivery_id": "7fade5d5-9395-4a00-800a-549f255e3b4a",
    "vendor_id": "f96ed92f-cac6-42b9-816e-583ba91a77ec",
    "vendor_name": "ProTech Safety Gear - Q",
    "delivery_date": "2026-01-23",
    "items_delivered": "Communication Equipment",
    "quantity": 235,
    "on_time_status": true,
    "quality_score": 4.91,
    "defect_count": 0,
    "issue_description": ""
  },
  {
    "delivery_id": "57829d6c-3b51-4330-867a-215a94065f8f",
    "vendor_id": "a28ad32e-55b0-41ee-95e7-d83dda8eac2a",
    "vendor_name": "FireShield Technologies - V",
    "delivery_date": "2025-08-02",
    "items_delivered": "Safety Helmets",
    "quantity": 358,
    "on_time_status": true,
    "quality_score": 4.25,
    "defect_count": 1,
    "issue_description": ""
  },
  {
    "delivery_id": "4c0fce20-0b5c-4b42-8a59-a7c5cf171ac5",
    "vendor_id": "f6a95519-0601-4e89-912d-a94ad74baba5",
    "vendor_name": "National Fire Services - G",
    "delivery_date": "2025-11-11",
    "items_delivered": "Communication Equipment",
    "quantity": 72,
    "on_time_status": false,
    "quality_score": 4.75,
    "defect_count": 4,
    "issue_description": "Incomplete order"
  },
  {
    "delivery_id": "2b85238f-ee11-4126-8b1d-00dc622a37b6",
    "vendor_id": "1660174a-e73a-4504-bcfa-aec7cd48726d",
    "vendor_name": "Guardian Safety Solutions - D",
    "delivery_date": "2025-10-05",
    "items_delivered": "Protective Gear",
    "quantity": 460,
    "on_time_status": true,
    "quality_score": 4.28,
    "defect_count": 2,
    "issue_description": ""
  },
  {
    "delivery_id": "0cfe77f9-1a95-4350-b854-543d82979f68",
    "vendor_id": "ed7eee20-a6ca-4ee8-b54a-452eac70c056",
    "vendor_name": "National Fire Services - H",
    "delivery_date": "2025-03-18",
    "items_delivered": "Safety Helmets",
    "quantity": 371,
    "on_time_status": true,
    "quality_score": 3.82,
    "defect_count": 2,
    "issue_description": ""
  },
  {
    "delivery_id": "7e085ee2-0e68-4b8e-86d9-22748b4fd61b",
    "vendor_id": "29aa9588-6658-4615-b904-23ca2df08575",
    "vendor_name": "Guardian Safety Solutions - E",
    "delivery_date": "2026-01-23",
    "items_delivered": "Fire Hoses",
    "quantity": 83,
    "on_time_status": false,
    "quality_score": 3.69,
    "defect_count": 0,
    "issue_description": "Delayed delivery"
  },
  {
    "delivery_id": "f9dba3dc-126c-4947-a9a8-91ee47e21c35",
    "vendor_id": "8dcdf82f-5127-47e4-9106-b207e5486bc5",
    "vendor_name": "SafeGuard Equipment Co - F",
    "delivery_date": "2025-03-06",
    "items_delivered": "Fire Hoses",
    "quantity": 263,
    "on_time_status": false,
    "quality_score": 4.75,
    "defect_count": 1,
    "issue_description": "Documentation missing"
  },
  {
    "delivery_id": "b94de788-8658-483e-bd84-633287a5fb4b",
    "vendor_id": "27614199-6165-4d66-8642-981b0eb1efbe",
    "vendor_name": "Advanced Safety Equipment - B",
    "delivery_date": "2025-02-13",
    "items_delivered": "Protective Gear",
    "quantity": 49,
    "on_time_status": true,
    "quality_score": 3.74,
    "defect_count": 2,
    "issue_description": "Documentation missing"
  },
  {
    "delivery_id": "6759f24d-7a33-4b0d-afbf-6ab4aa0627bf",
    "vendor_id": "fb0f4a3c-054d-406f-9a53-fd19d31957c1",
    "vendor_name": "SecureLife Fire Systems - N",
    "delivery_date": "2025-09-06",
    "items_delivered": "Communication Equipment",
    "quantity": 384,
    "on_time_status": true,
    "quality_score": 3.77,
    "defect_count": 2,
    "issue_description": ""
  },
  {
    "delivery_id": "e2b16acf-171a-4870-9e81-f4f4f11fbfa3",
    "vendor_id": "0ee45aad-7218-4fbd-a019-7808cf810307",
    "vendor_name": "SecureLife Fire Systems - Y",
    "delivery_date": "2025-04-16",
    "items_delivered": "Fire Extinguishers",
    "quantity": 75,
    "on_time_status": true,
    "quality_score": 3.72,
    "defect_count": 0,
    "issue_description": ""
  },
  {
    "delivery_id": "a9d3dd22-08c1-4452-8169-dfae28d332a3",
    "vendor_id": "b4dd8826-1cf6-4af2-b0e0-d14b25f01eec",
    "vendor_name": "Alert Fire Protection - Q",
    "delivery_date": "2025-09-11",
    "items_delivered": "Breathing Apparatus",
    "quantity": 55,
    "on_time_status": true,
    "quality_score": 4.62,
    "defect_count": 0,
    "issue_description": ""
  },
  {
    "delivery_id": "fdc88d8e-7d66-4617-93ea-8c5021a15eba",
    "vendor_id": "72ef11ee-138b-42da-9031-ff79e7425bb1",
    "vendor_name": "Guardian Safety Solutions - I",
    "delivery_date": "2025-06-10",
    "items_delivered": "Fire Extinguishers",
    "quantity": 218,
    "on_time_status": true,
    "quality_score": 4.83,
    "defect_count": 0,
    "issue_description": ""
  },
  {
    "delivery_id": "9d320395-0511-4670-a892-ac55c6536558",
    "vendor_id": "916af05b-1000-4b91-868e-1582a65c8324",
    "vendor_name": "ProTech Safety Gear - M",
    "delivery_date": "2025-09-23",
    "items_delivered": "Breathing Apparatus",
    "quantity": 498,
    "on_time_status": true,
    "quality_score": 3.63,
    "defect_count": 2,
    "issue_description": ""
  },
  {
    "delivery_id": "1a8917d4-e6b4-430f-b059-361bba2a7788",
    "vendor_id": "9f95005e-ad9e-473e-83a9-602256353a95",
    "vendor_name": "Advanced Safety Equipment - N",
    "delivery_date": "2025-08-22",
    "items_delivered": "Breathing Apparatus",
    "quantity": 173,
    "on_time_status": false,
    "quality_score": 3.87,
    "defect_count": 1,
    "issue_description": "Minor packaging damage"
  },
  {
    "delivery_id": "7e8b72c3-c993-4892-a4a4-553cf50db075",
    "vendor_id": "a28ad32e-55b0-41ee-95e7-d83dda8eac2a",
    "vendor_name": "FireShield Technologies - V",
    "delivery_date": "2025-03-20",
    "items_delivered": "Fire Extinguishers",
    "quantity": 293,
    "on_time_status": false,
    "quality_score": 4.1,
    "defect_count": 3,
    "issue_description": "Documentation missing"
  },
  {
    "delivery_id": "c1cf10be-8726-4ab3-8d25-9393403e6b6a",
    "vendor_id": "fa658a7b-1f0a-4fec-a36d-c270b8ac2e88",
    "vendor_name": "Advanced Safety Equipment - L",
    "delivery_date": "2025-06-24",
    "items_delivered": "Fire Hoses",
    "quantity": 392,
    "on_time_status": false,
    "quality_score": 4.67,
    "defect_count": 4,
    "issue_description": "Minor packaging damage"
  },
  {
    "delivery_id": "5604803f-dedf-476c-a156-43e8a1524506",
    "vendor_id": "a16c821a-6baf-4910-a107-fa60bd06c870",
    "vendor_name": "Blaze Control Systems - V",
    "delivery_date": "2025-11-10",
    "items_delivered": "Communication Equipment",
    "quantity": 325,
    "on_time_status": true,
    "quality_score": 3.97,
    "defect_count": 1,
    "issue_description": ""
  },
  {
    "delivery_id": "4aa8eac6-676e-4727-91ce-70b368371d61",
    "vendor_id": "5ee342c3-ad83-45ea-8de4-b9b4e9729227",
    "vendor_name": "RapidResponse Suppliers - X",
    "delivery_date": "2025-06-25",
    "items_delivered": "Breathing Apparatus",
    "quantity": 480,
    "on_time_status": true,
    "quality_score": 4.45,
    "defect_count": 1,
    "issue_description": ""
  },
  {
    "delivery_id": "937cca97-3854-4f64-ab86-cfeb067fa3cc",
    "vendor_id": "bd6dd705-a44c-4009-91d9-20de59efd6c2",
    "vendor_name": "Alert Fire Protection - S",
    "delivery_date": "2025-06-29",
    "items_delivered": "Safety Helmets",
    "quantity": 495,
    "on_time_status": false,
    "quality_score": 4.69,
    "defect_count": 4,
    "issue_description": "Quality issues"
  },
  {
    "delivery_id": "c025fd52-47a1-425e-ae02-43b13c66dfee",
    "vendor_id": "fb0f4a3c-054d-406f-9a53-fd19d31957c1",
    "vendor_name": "SecureLife Fire Systems - N",
    "delivery_date": "2026-01-22",
    "items_delivered": "Breathing Apparatus",
    "quantity": 443,
    "on_time_status": true,
    "quality_score": 4.47,
    "defect_count": 1,
    "issue_description": ""
  },
  {
    "delivery_id": "b132c831-2720-4d1e-87bd-54e862333f91",
    "vendor_id": "72ef11ee-138b-42da-9031-ff79e7425bb1",
    "vendor_name": "Guardian Safety Solutions - I",
    "delivery_date": "2025-10-28",
    "items_delivered": "Fire Hoses",
    "quantity": 492,
    "on_time_status": true,
    "quality_score": 4.66,
    "defect_count": 2,
    "issue_description": ""
  },
  {
    "delivery_id": "a85e74ea-581d-441a-a648-747367f9394d",
    "vendor_id": "882d6bad-c283-46b6-90f1-d473e25efdcd",
    "vendor_name": "Guardian Safety Solutions - O",
    "delivery_date": "2025-02-05",
    "items_delivered": "Safety Helmets",
    "quantity": 30,
    "on_time_status": true,
    "quality_score": 4.73,
    "defect_count": 2,
    "issue_description": ""
  },
  {
    "delivery_id": "b110934a-5277-4173-8ba4-777978d61cf7",
    "vendor_id": "af157658-9e1c-4dc4-980d-4426b95a344e",
    "vendor_name": "Blaze Control Systems - A",
    "delivery_date": "2025-05-27",
    "items_delivered": "Fire Hoses",
    "quantity": 273,
    "on_time_status": true,
    "quality_score": 4.0,
    "defect_count": 0,
    "issue_description": ""
  },
  {
    "delivery_id": "9aef6396-c414-4530-9958-10e00cfe8f3a",
    "vendor_id": "bd6dd705-a44c-4009-91d9-20de59efd6c2",
    "vendor_name": "Alert Fire Protection - S",
    "delivery_date": "2025-12-23",
    "items_delivered": "Fire Extinguishers",
    "quantity": 458,
    "on_time_status": true,
    "quality_score": 4.12,
    "defect_count": 1,
    "issue_description": ""
  },
  {
    "delivery_id": "504fbb61-3007-44cd-9168-71d7084a8683",
    "vendor_id": "27614199-6165-4d66-8642-981b0eb1efbe",
    "vendor_name": "Advanced Safety Equipment - B",
    "delivery_date": "2025-02-09",
    "items_delivered": "Safety Helmets",
    "quantity": 399,
    "on_time_status": true,
    "quality_score": 4.94,
    "defect_count": 0,
    "issue_description": ""
  },
  {
    "delivery_id": "cf444ed6-61af-4254-b0fa-bd4123215c25",
    "vendor_id": "a28ad32e-55b0-41ee-95e7-d83dda8eac2a",
    "vendor_name": "FireShield Technologies - V",
    "delivery_date": "2025-09-08",
    "items_delivered": "Breathing Apparatus",
    "quantity": 110,
    "on_time_status": true,
    "quality_score": 3.59,
    "defect_count": 2,
    "issue_description": ""
  },
  {
    "delivery_id": "148d7d7b-5768-4ff1-a375-0c894d0d1b6a",
    "vendor_id": "e6d913ac-e1c0-4924-816b-caeb155a96a9",
    "vendor_name": "FireShield Technologies - T",
    "delivery_date": "2025-12-29",
    "items_delivered": "Communication Equipment",
    "quantity": 145,
    "on_time_status": true,
    "quality_score": 4.56,
    "defect_count": 2,
    "issue_description": ""
  },
  {
    "delivery_id": "57b5d70f-3e4d-41e4-b229-31edd999e95a",
    "vendor_id": "757511b3-18d6-46e9-8886-eddc26824fca",
    "vendor_name": "ProTech Safety Gear - W",
    "delivery_date": "2025-12-02",
    "items_delivered": "Fire Extinguishers",
    "quantity": 205,
    "on_time_status": true,
    "quality_score": 4.65,
    "defect_count": 1,
    "issue_description": "Delayed delivery"
  },
  {
    "delivery_id": "4a7e863a-b9a2-496e-a00a-d29a60f69f3d",
    "vendor_id": "1cf99934-8e1b-4468-ad91-ac9f7506b9f7",
    "vendor_name": "Emergency Response Solutions - W",
    "delivery_date": "2025-02-03",
    "items_delivered": "Fire Hoses",
    "quantity": 213,
    "on_time_status": false,
    "quality_score": 3.62,
    "defect_count": 5,
    "issue_description": "Delayed delivery"
  },
  {
    "delivery_id": "052e2d64-5f0e-44e7-802d-f4b5ea61f0d7",
    "vendor_id": "27614199-6165-4d66-8642-981b0eb1efbe",
    "vendor_name": "Advanced Safety Equipment - B",
    "delivery_date": "2025-03-10",
    "items_delivered": "Fire Hoses",
    "quantity": 474,
    "on_time_status": true,
    "quality_score": 4.09,
    "defect_count": 1,
    "issue_description": "Delayed delivery"
  },
  {
    "delivery_id": "a2867880-ae28-4c70-bc2b-2e96488a6cc3",
    "vendor_id": "72ef11ee-138b-42da-9031-ff79e7425bb1",
    "vendor_name": "Guardian Safety Solutions - I",
    "delivery_date": "2025-10-18",
    "items_delivered": "Communication Equipment",
    "quantity": 371,
    "on_time_status": false,
    "quality_score": 3.85,
    "defect_count": 2,
    "issue_description": "Delayed delivery"
  },
  {
    "delivery_id": "bb8a6421-992a-41c9-889f-f3f27059cb2a",
    "vendor_id": "ee54677b-a315-4170-9a1b-eb8ff0b6dff0",
    "vendor_name": "Blaze Control Systems - E",
    "delivery_date": "2025-09-21",
    "items_delivered": "Breathing Apparatus",
    "quantity": 196,
    "on_time_status": true,
    "quality_score": 4.09,
    "defect_count": 0,
    "issue_description": ""
  },
  {
    "delivery_id": "3d0277e8-233a-468c-afd2-c0fbc36aaba6",
    "vendor_id": "30ea2b71-2891-4974-a812-5b7e193dc75f",
    "vendor_name": "Guardian Safety Solutions - D",
    "delivery_date": "2025-02-12",
    "items_delivered": "Communication Equipment",
    "quantity": 96,
    "on_time_status": true,
    "quality_score": 4.32,
    "defect_count": 0,
    "issue_description": ""
  },
  {
    "delivery_id": "01f141f6-573e-4304-8bd1-1cd356576529",
    "vendor_id": "b1e4a21b-f759-4457-ae30-18db2fc6fe94",
    "vendor_name": "National Fire Services - U",
    "delivery_date": "2025-09-17",
    "items_delivered": "Fire Extinguishers",
    "quantity": 482,
    "on_time_status": true,
    "quality_score": 4.84,
    "defect_count": 2,
    "issue_description": ""
  },
  {
    "delivery_id": "dad2b4af-7e98-4e9b-8f07-c78f22f6e8a0",
    "vendor_id": "27614199-6165-4d66-8642-981b0eb1efbe",
    "vendor_name": "Advanced Safety Equipment - B",
    "delivery_date": "2025-12-11",
    "items_delivered": "Safety Helmets",
    "quantity": 214,
    "on_time_status": false,
    "quality_score": 4.01,
    "defect_count": 5,
    "issue_description": "Delayed delivery"
  },
  {
    "delivery_id": "983cf3fa-a573-47dc-bcdc-cd058640edc3",
    "vendor_id": "ed7eee20-a6ca-4ee8-b54a-452eac70c056",
    "vendor_name": "National Fire Services - H",
    "delivery_date": "2025-05-19",
    "items_delivered": "Safety Helmets",
    "quantity": 444,
    "on_time_status": true,
    "quality_score": 3.86,
    "defect_count": 1,
    "issue_description": ""
  },
  {
    "delivery_id": "da7828c7-6210-4af5-b6a1-64754d0f6ac1",
    "vendor_id": "882d6bad-c283-46b6-90f1-d473e25efdcd",
    "vendor_name": "Guardian Safety Solutions - O",
    "delivery_date": "2025-06-21",
    "items_delivered": "Communication Equipment",
    "quantity": 298,
    "on_time_status": true,
    "quality_score": 3.7,
    "defect_count": 0,
    "issue_description": ""
  },
  {
    "delivery_id": "4eb6c315-3a96-44a4-8b72-4dd4258e482d",
    "vendor_id": "7054182b-61df-4dec-9fe2-77a0a7054814",
    "vendor_name": "Emergency Response Solutions - J",
    "delivery_date": "2025-05-08",
    "items_delivered": "Safety Helmets",
    "quantity": 161,
    "on_time_status": true,
    "quality_score": 3.66,
    "defect_count": 1,
    "issue_description": "Quality issues"
  },
  {
    "delivery_id": "d23c3e9d-ec0a-4c36-8f1a-d9d42615fceb",
    "vendor_id": "27614199-6165-4d66-8642-981b0eb1efbe",
    "vendor_name": "Advanced Safety Equipment - B",
    "delivery_date": "2025-12-21",
    "items_delivered": "Communication Equipment",
    "quantity": 497,
    "on_time_status": true,
    "quality_score": 4.3,
    "defect_count": 1,
    "issue_description": "Quality issues"
  },
  {
    "delivery_id": "48d1be58-59b2-4c24-a40c-87944292686d",
    "vendor_id": "5ee342c3-ad83-45ea-8de4-b9b4e9729227",
    "vendor_name": "RapidResponse Suppliers - X",
    "delivery_date": "2025-05-13",
    "items_delivered": "Communication Equipment",
    "quantity": 216,
    "on_time_status": true,
    "quality_score": 4.97,
    "defect_count": 0,
    "issue_description": "Incomplete order"
  },
  {
    "delivery_id": "046c97de-45f7-4fb8-b312-301377969911",
    "vendor_id": "44f3f137-6d1a-4e85-a467-b9c4e668d880",
    "vendor_name": "Advanced Safety Equipment - T",
    "delivery_date": "2025-10-09",
    "items_delivered": "Protective Gear",
    "quantity": 73,
    "on_time_status": false,
    "quality_score": 3.62,
    "defect_count": 3,
    "issue_description": "Incomplete order"
  },
  {
    "delivery_id": "5c83e622-a39e-4812-91af-543ffbc6b90d",
    "vendor_id": "72ef11ee-138b-42da-9031-ff79e7425bb1",
    "vendor_name": "Guardian Safety Solutions - I",
    "delivery_date": "2025-06-16",
    "items_delivered": "Safety Helmets",
    "quantity": 201,
    "on_time_status": false,
    "quality_score": 3.52,
    "defect_count": 0,
    "issue_description": "Minor packaging damage"
  },
  {
    "delivery_id": "47efdd2b-21c1-49af-838e-a072d395ba62",
    "vendor_id": "0ee45aad-7218-4fbd-a019-7808cf810307",
    "vendor_name": "SecureLife Fire Systems - Y",
    "delivery_date": "2026-01-07",
    "items_delivered": "Fire Extinguishers",
    "quantity": 250,
    "on_time_status": true,
    "quality_score": 4.02,
    "defect_count": 2,
    "issue_description": ""
  },
  {
    "delivery_id": "c043021b-4753-401b-af46-2ec5fb0139ac",
    "vendor_id": "a16c821a-6baf-4910-a107-fa60bd06c870",
    "vendor_name": "Blaze Control Systems - V",
    "delivery_date": "2025-07-11",
    "items_delivered": "Protective Gear",
    "quantity": 287,
    "on_time_status": true,
    "quality_score": 4.69,
    "defect_count": 1,
    "issue_description": ""
  },
  {
    "delivery_id": "7d2d3feb-f0c2-4030-91b4-49dc06f15531",
    "vendor_id": "7a522c24-b040-4be9-a9be-ac1b92af655a",
    "vendor_name": "Blaze Control Systems - C",
    "delivery_date": "2025-05-12",
    "items_delivered": "Breathing Apparatus",
    "quantity": 140,
    "on_time_status": false,
    "quality_score": 3.78,
    "defect_count": 1,
    "issue_description": "Delayed delivery"
  },
  {
    "delivery_id": "0c7ce6b4-5a67-4386-a8ab-e3ca3a9c14f2",
    "vendor_id": "29aa9588-6658-4615-b904-23ca2df08575",
    "vendor_name": "Guardian Safety Solutions - E",
    "delivery_date": "2025-09-28",
    "items_delivered": "Fire Hoses",
    "quantity": 406,
    "on_time_status": true,
    "quality_score": 3.85,
    "defect_count": 0,
    "issue_description": ""
  },
  {
    "delivery_id": "ae534766-ad51-45f6-b3b9-956df9fbccc4",
    "vendor_id": "9f95005e-ad9e-473e-83a9-602256353a95",
    "vendor_name": "Advanced Safety Equipment - N",
    "delivery_date": "2025-12-31",
    "items_delivered": "Fire Hoses",
    "quantity": 76,
    "on_time_status": false,
    "quality_score": 3.6,
    "defect_count": 5,
    "issue_description": "Quality issues"
  },
  {
    "delivery_id": "ce557263-683b-46f5-8ba9-d86584aed9ff",
    "vendor_id": "7a522c24-b040-4be9-a9be-ac1b92af655a",
    "vendor_name": "Blaze Control Systems - C",
    "delivery_date": "2025-05-31",
    "items_delivered": "Communication Equipment",
    "quantity": 20,
    "on_time_status": false,
    "quality_score": 4.08,
    "defect_count": 4,
    "issue_description": "Quality issues"
  },
  {
    "delivery_id": "6fd4e724-5cf3-4df7-ad4e-83c768e4d4ba",
    "vendor_id": "f6a95519-0601-4e89-912d-a94ad74baba5",
    "vendor_name": "National Fire Services - G",
    "delivery_date": "2025-07-10",
    "items_delivered": "Fire Extinguishers",
    "quantity": 314,
    "on_time_status": true,
    "quality_score": 3.78,
    "defect_count": 1,
    "issue_description": ""
  },
  {
    "delivery_id": "59c7894c-15a1-4b71-96ce-27787760101f",
    "vendor_id": "27614199-6165-4d66-8642-981b0eb1efbe",
    "vendor_name": "Advanced Safety Equipment - B",
    "delivery_date": "2025-09-04",
    "items_delivered": "Safety Helmets",
    "quantity": 189,
    "on_time_status": true,
    "quality_score": 4.07,
    "defect_count": 0,
    "issue_description": ""
  },
  {
    "delivery_id": "1756005f-1126-443f-8f3a-5cde65c979f7",
    "vendor_id": "1660174a-e73a-4504-bcfa-aec7cd48726d",
    "vendor_name": "Guardian Safety Solutions - D",
    "delivery_date": "2025-08-03",
    "items_delivered": "Fire Extinguishers",
    "quantity": 29,
    "on_time_status": true,
    "quality_score": 4.5,
    "defect_count": 2,
    "issue_description": ""
  },
  {
    "delivery_id": "d9c2ea30-2340-4598-87e3-d672cdcfe738",
    "vendor_id": "f6a95519-0601-4e89-912d-a94ad74baba5",
    "vendor_name": "National Fire Services - G",
    "delivery_date": "2025-12-20",
    "items_delivered": "Fire Extinguishers",
    "quantity": 170,
    "on_time_status": true,
    "quality_score": 3.75,
    "defect_count": 1,
    "issue_description": "Minor packaging damage"
  },
  {
    "delivery_id": "3e9cb0e5-407e-4885-89c3-b06035c0c8ca",
    "vendor_id": "9ca723b9-570c-4a06-91fa-34a7298caff8",
    "vendor_name": "FireSafe India Pvt Ltd - P",
    "delivery_date": "2025-07-10",
    "items_delivered": "Protective Gear",
    "quantity": 37,
    "on_time_status": false,
    "quality_score": 3.57,
    "defect_count": 1,
    "issue_description": "Incomplete order"
  },
  {
    "delivery_id": "14f0a183-167d-44fa-8e3e-152f4343fb95",
    "vendor_id": "27614199-6165-4d66-8642-981b0eb1efbe",
    "vendor_name": "Advanced Safety Equipment - B",
    "delivery_date": "2025-08-27",
    "items_delivered": "Fire Extinguishers",
    "quantity": 125,
    "on_time_status": true,
    "quality_score": 3.67,
    "defect_count": 2,
    "issue_description": "Documentation missing"
  },
  {
    "delivery_id": "13e6ae60-fe76-43ff-b88d-5e97eb6bbdd3",
    "vendor_id": "bd6dd705-a44c-4009-91d9-20de59efd6c2",
    "vendor_name": "Alert Fire Protection - S",
    "delivery_date": "2025-03-09",
    "items_delivered": "Safety Helmets",
    "quantity": 68,
    "on_time_status": true,
    "quality_score": 4.55,
    "defect_count": 2,
    "issue_description": ""
  },
  {
    "delivery_id": "915b99e4-06b0-4118-94cd-29af703a7670",
    "vendor_id": "05ec546b-598c-4435-8f5f-9e28000ac701",
    "vendor_name": "RapidResponse Suppliers - J",
    "delivery_date": "2025-12-16",
    "items_delivered": "Breathing Apparatus",
    "quantity": 20,
    "on_time_status": true,
    "quality_score": 4.36,
    "defect_count": 0,
    "issue_description": ""
  },
  {
    "delivery_id": "8612959e-508e-4543-a9de-bb1d9b85c1e3",
    "vendor_id": "6f3192f1-370d-4a7b-88ad-f66768146458",
    "vendor_name": "Guardian Safety Solutions - Z",
    "delivery_date": "2025-10-09",
    "items_delivered": "Fire Hoses",
    "quantity": 80,
    "on_time_status": true,
    "quality_score": 4.35,
    "defect_count": 1,
    "issue_description": ""
  },
  {
    "delivery_id": "53e9646a-0d3c-47ad-8ff3-447dc671eca9",
    "vendor_id": "a28ad32e-55b0-41ee-95e7-d83dda8eac2a",
    "vendor_name": "FireShield Technologies - V",
    "delivery_date": "2025-10-10",
    "items_delivered": "Communication Equipment",
    "quantity": 444,
    "on_time_status": false,
    "quality_score": 3.58,
    "defect_count": 4,
    "issue_description": "No issues"
  },
  {
    "delivery_id": "b1ab1b2a-b714-4cd9-85ab-360dff10b18b",
    "vendor_id": "8fe0cc12-6d82-41bb-9fa0-422dd9c8d13c",
    "vendor_name": "FireSafe India Pvt Ltd - K",
    "delivery_date": "2025-09-26",
    "items_delivered": "Communication Equipment",
    "quantity": 73,
    "on_time_status": true,
    "quality_score": 4.18,
    "defect_count": 1,
    "issue_description": ""
  },
  {
    "delivery_id": "28f810e2-52ed-43f1-9340-dda4ce76eb49",
    "vendor_id": "a27beb2d-c353-4be0-9a4c-477a3faa45b5",
    "vendor_name": "Guardian Safety Solutions - F",
    "delivery_date": "2025-06-17",
    "items_delivered": "Safety Helmets",
    "quantity": 61,
    "on_time_status": true,
    "quality_score": 4.21,
    "defect_count": 2,
    "issue_description": "Minor packaging damage"
  },
  {
    "delivery_id": "db1f0024-e5b6-41b8-86db-fc43b438e5cc",
    "vendor_id": "8d93fcaa-b572-43a9-9c47-05acf2e14ffc",
    "vendor_name": "FireSafe India Pvt Ltd - H",
    "delivery_date": "2025-04-21",
    "items_delivered": "Communication Equipment",
    "quantity": 305,
    "on_time_status": true,
    "quality_score": 4.58,
    "defect_count": 2,
    "issue_description": ""
  },
  {
    "delivery_id": "3d3b4077-3127-48da-8e9b-496796f0b085",
    "vendor_id": "aff23462-f0db-4391-9713-552269e81c5f",
    "vendor_name": "SecureLife Fire Systems - O",
    "delivery_date": "2025-04-17",
    "items_delivered": "Fire Hoses",
    "quantity": 186,
    "on_time_status": true,
    "quality_score": 3.62,
    "defect_count": 0,
    "issue_description": ""
  },
  {
    "delivery_id": "01ea677c-981c-4492-93eb-ce2fbb155c2c",
    "vendor_id": "34897448-66b2-431f-9c3e-b0cf10530c14",
    "vendor_name": "National Fire Services - S",
    "delivery_date": "2025-10-05",
    "items_delivered": "Fire Hoses",
    "quantity": 229,
    "on_time_status": false,
    "quality_score": 3.61,
    "defect_count": 1,
    "issue_description": "Incomplete order"
  },
  {
    "delivery_id": "49baf027-cfcb-4eb1-a46e-ec977f6b63fb",
    "vendor_id": "f392ea5e-10f1-4444-b821-fe9b74aa6a22",
    "vendor_name": "Advanced Safety Equipment - X",
    "delivery_date": "2025-06-20",
    "items_delivered": "Fire Extinguishers",
    "quantity": 353,
    "on_time_status": false,
    "quality_score": 4.67,
    "defect_count": 2,
    "issue_description": "Documentation missing"
  },
  {
    "delivery_id": "da7b194f-ddb5-4eb3-b67c-425ddbe1eba4",
    "vendor_id": "882d6bad-c283-46b6-90f1-d473e25efdcd",
    "vendor_name": "Guardian Safety Solutions - O",
    "delivery_date": "2025-08-28",
    "items_delivered": "Communication Equipment",
    "quantity": 121,
    "on_time_status": true,
    "quality_score": 4.0,
    "defect_count": 1,
    "issue_description": "Incomplete order"
  },
  {
    "delivery_id": "8ac2a459-b99d-43b2-8257-b5e886ac791c",
    "vendor_id": "d9a9634b-ebe9-42b4-9254-2e7a37916db5",
    "vendor_name": "ProTech Safety Gear - R",
    "delivery_date": "2026-01-11",
    "items_delivered": "Communication Equipment",
    "quantity": 132,
    "on_time_status": true,
    "quality_score": 4.85,
    "defect_count": 0,
    "issue_description": ""
  },
  {
    "delivery_id": "696c1039-359d-4de6-8c8a-389f97cfd8ad",
    "vendor_id": "34897448-66b2-431f-9c3e-b0cf10530c14",
    "vendor_name": "National Fire Services - S",
    "delivery_date": "2025-06-14",
    "items_delivered": "Safety Helmets",
    "quantity": 138,
    "on_time_status": true,
    "quality_score": 4.2,
    "defect_count": 2,
    "issue_description": "Delayed delivery"
  },
  {
    "delivery_id": "0faab20e-0b15-486a-97af-24e30aafd5d7",
    "vendor_id": "af157658-9e1c-4dc4-980d-4426b95a344e",
    "vendor_name": "Blaze Control Systems - A",
    "delivery_date": "2025-04-05",
    "items_delivered": "Fire Extinguishers",
    "quantity": 129,
    "on_time_status": true,
    "quality_score": 3.52,
    "defect_count": 1,
    "issue_description": ""
  },
  {
    "delivery_id": "126e27ed-19fb-4226-a001-610214e34605",
    "vendor_id": "72ef11ee-138b-42da-9031-ff79e7425bb1",
    "vendor_name": "Guardian Safety Solutions - I",
    "delivery_date": "2025-12-17",
    "items_delivered": "Safety Helmets",
    "quantity": 116,
    "on_time_status": false,
    "quality_score": 4.97,
    "defect_count": 3,
    "issue_description": "Documentation missing"
  },
  {
    "delivery_id": "9bad1e74-cd0f-4835-b3f2-55a1fdbf31e4",
    "vendor_id": "f6a95519-0601-4e89-912d-a94ad74baba5",
    "vendor_name": "National Fire Services - G",
    "delivery_date": "2025-07-02",
    "items_delivered": "Breathing Apparatus",
    "quantity": 26,
    "on_time_status": true,
    "quality_score": 4.86,
    "defect_count": 0,
    "issue_description": ""
  },
  {
    "delivery_id": "b015f939-f1e1-48a9-bd4e-a8569dbb03ab",
    "vendor_id": "44f3f137-6d1a-4e85-a467-b9c4e668d880",
    "vendor_name": "Advanced Safety Equipment - T",
    "delivery_date": "2025-08-06",
    "items_delivered": "Breathing Apparatus",
    "quantity": 294,
    "on_time_status": true,
    "quality_score": 4.89,
    "defect_count": 2,
    "issue_description": ""
  },
  {
    "delivery_id": "8645d3ec-b0f8-4bde-9942-4743dad3774f",
    "vendor_id": "ee54677b-a315-4170-9a1b-eb8ff0b6dff0",
    "vendor_name": "Blaze Control Systems - E",
    "delivery_date": "2025-10-16",
    "items_delivered": "Safety Helmets",
    "quantity": 145,
    "on_time_status": true,
    "quality_score": 3.77,
    "defect_count": 2,
    "issue_description": "No issues"
  },
  {
    "delivery_id": "64e2b4eb-87ed-4b6d-8a98-2d6f71adb57e",
    "vendor_id": "b1e4a21b-f759-4457-ae30-18db2fc6fe94",
    "vendor_name": "National Fire Services - U",
    "delivery_date": "2025-10-14",
    "items_delivered": "Safety Helmets",
    "quantity": 223,
    "on_time_status": true,
    "quality_score": 4.8,
    "defect_count": 2,
    "issue_description": ""
  },
  {
    "delivery_id": "c0243093-4ab6-4e3c-ba71-c132de06ca0b",
    "vendor_id": "a28ad32e-55b0-41ee-95e7-d83dda8eac2a",
    "vendor_name": "FireShield Technologies - V",
    "delivery_date": "2025-06-25",
    "items_delivered": "Fire Extinguishers",
    "quantity": 254,
    "on_time_status": true,
    "quality_score": 4.38,
    "defect_count": 0,
    "issue_description": ""
  },
  {
    "delivery_id": "2841fff5-b4c9-4fb3-82e7-84da67838030",
    "vendor_id": "4ee2786a-2917-4a1f-92ec-976e27cf8a2d",
    "vendor_name": "FireSafe India Pvt Ltd - L",
    "delivery_date": "2025-11-10",
    "items_delivered": "Fire Extinguishers",
    "quantity": 306,
    "on_time_status": true,
    "quality_score": 4.85,
    "defect_count": 0,
    "issue_description": ""
  },
  {
    "delivery_id": "058d4ee7-425c-4c37-83e3-92dee7e373ce",
    "vendor_id": "fb0f4a3c-054d-406f-9a53-fd19d31957c1",
    "vendor_name": "SecureLife Fire Systems - N",
    "delivery_date": "2025-07-25",
    "items_delivered": "Breathing Apparatus",
    "quantity": 315,
    "on_time_status": true,
    "quality_score": 4.94,
    "defect_count": 0,
    "issue_description": ""
  },
  {
    "delivery_id": "d7f45c5c-b778-49e2-850c-50aa2eca07ff",
    "vendor_id": "cf6ccc2a-ef39-4df3-8610-cb7e9cda5773",
    "vendor_name": "Guardian Safety Solutions - I",
    "delivery_date": "2025-08-07",
    "items_delivered": "Protective Gear",
    "quantity": 255,
    "on_time_status": true,
    "quality_score": 4.88,
    "defect_count": 1,
    "issue_description": ""
  },
  {
    "delivery_id": "ae9ea42e-0a12-43a5-b427-0458454a0e1c",
    "vendor_id": "30ea2b71-2891-4974-a812-5b7e193dc75f",
    "vendor_name": "Guardian Safety Solutions - D",
    "delivery_date": "2025-02-06",
    "items_delivered": "Breathing Apparatus",
    "quantity": 294,
    "on_time_status": true,
    "quality_score": 3.59,
    "defect_count": 0,
    "issue_description": ""
  },
  {
    "delivery_id": "6115a11b-b7d4-44aa-8d37-46e044066936",
    "vendor_id": "f6a95519-0601-4e89-912d-a94ad74baba5",
    "vendor_name": "National Fire Services - G",
    "delivery_date": "2025-03-04",
    "items_delivered": "Protective Gear",
    "quantity": 344,
    "on_time_status": false,
    "quality_score": 4.92,
    "defect_count": 0,
    "issue_description": "Delayed delivery"
  },
  {
    "delivery_id": "a538c738-4c2a-48e3-b042-c364fc413c7e",
    "vendor_id": "882d6bad-c283-46b6-90f1-d473e25efdcd",
    "vendor_name": "Guardian Safety Solutions - O",
    "delivery_date": "2025-05-19",
    "items_delivered": "Communication Equipment",
    "quantity": 340,
    "on_time_status": false,
    "quality_score": 3.72,
    "defect_count": 3,
    "issue_description": "Quality issues"
  },
  {
    "delivery_id": "00acb6a3-b3b8-4917-b2f3-609df8ae8ff4",
    "vendor_id": "0fcdf246-8886-4e49-bda0-d801bf0e1281",
    "vendor_name": "Alert Fire Protection - G",
    "delivery_date": "2025-07-15",
    "items_delivered": "Protective Gear",
    "quantity": 123,
    "on_time_status": true,
    "quality_score": 4.25,
    "defect_count": 2,
    "issue_description": ""
  },
  {
    "delivery_id": "7d57e8de-858c-48e6-b9cb-d634763da431",
    "vendor_id": "8023d5ed-e138-4114-9b33-5b078e94c4aa",
    "vendor_name": "SecureLife Fire Systems - C",
    "delivery_date": "2025-04-18",
    "items_delivered": "Safety Helmets",
    "quantity": 259,
    "on_time_status": true,
    "quality_score": 3.66,
    "defect_count": 1,
    "issue_description": ""
  },
  {
    "delivery_id": "ea7dd013-960a-4781-98c5-25631f22dcdb",
    "vendor_id": "0ee45aad-7218-4fbd-a019-7808cf810307",
    "vendor_name": "SecureLife Fire Systems - Y",
    "delivery_date": "2025-02-11",
    "items_delivered": "Breathing Apparatus",
    "quantity": 70,
    "on_time_status": true,
    "quality_score": 4.1,
    "defect_count": 2,
    "issue_description": ""
  },
  {
    "delivery_id": "5e592fa0-e081-4579-9347-2abb63e5e74f",
    "vendor_id": "cf6ccc2a-ef39-4df3-8610-cb7e9cda5773",
    "vendor_name": "Guardian Safety Solutions - I",
    "delivery_date": "2025-12-13",
    "items_delivered": "Fire Hoses",
    "quantity": 367,
    "on_time_status": true,
    "quality_score": 3.87,
    "defect_count": 0,
    "issue_description": "Quality issues"
  },
  {
    "delivery_id": "2e0ecf78-8108-4e3f-9e7a-8cc1f92a948a",
    "vendor_id": "aff23462-f0db-4391-9713-552269e81c5f",
    "vendor_name": "SecureLife Fire Systems - O",
    "delivery_date": "2025-12-03",
    "items_delivered": "Communication Equipment",
    "quantity": 73,
    "on_time_status": true,
    "quality_score": 4.75,
    "defect_count": 2,
    "issue_description": ""
  },
  {
    "delivery_id": "eb114299-533a-4cc8-8493-00144f868e0b",
    "vendor_id": "882d6bad-c283-46b6-90f1-d473e25efdcd",
    "vendor_name": "Guardian Safety Solutions - O",
    "delivery_date": "2025-04-04",
    "items_delivered": "Fire Extinguishers",
    "quantity": 216,
    "on_time_status": false,
    "quality_score": 3.87,
    "defect_count": 3,
    "issue_description": "Incomplete order"
  },
  {
    "delivery_id": "1b3e5f70-45a8-4351-adff-68934c5f9dfa",
    "vendor_id": "fb0f4a3c-054d-406f-9a53-fd19d31957c1",
    "vendor_name": "SecureLife Fire Systems - N",
    "delivery_date": "2025-09-28",
    "items_delivered": "Breathing Apparatus",
    "quantity": 307,
    "on_time_status": true,
    "quality_score": 3.78,
    "defect_count": 1,
    "issue_description": "No issues"
  },
  {
    "delivery_id": "f5c946d8-62f7-4214-b39a-5fba319cbd53",
    "vendor_id": "1660174a-e73a-4504-bcfa-aec7cd48726d",
    "vendor_name": "Guardian Safety Solutions - D",
    "delivery_date": "2025-10-08",
    "items_delivered": "Fire Hoses",
    "quantity": 373,
    "on_time_status": true,
    "quality_score": 3.61,
    "defect_count": 2,
    "issue_description": ""
  },
  {
    "delivery_id": "69b4bf7c-5a6c-4bb1-8c6e-e1e4a39ddb76",
    "vendor_id": "aff23462-f0db-4391-9713-552269e81c5f",
    "vendor_name": "SecureLife Fire Systems - O",
    "delivery_date": "2025-05-07",
    "items_delivered": "Fire Extinguishers",
    "quantity": 32,
    "on_time_status": true,
    "quality_score": 4.39,
    "defect_count": 2,
    "issue_description": ""
  },
  {
    "delivery_id": "5386320e-c5ab-445e-86cb-8df0a0ffaa89",
    "vendor_id": "9ca723b9-570c-4a06-91fa-34a7298caff8",
    "vendor_name": "FireSafe India Pvt Ltd - P",
    "delivery_date": "2025-12-31",
    "items_delivered": "Communication Equipment",
    "quantity": 73,
    "on_time_status": true,
    "quality_score": 4.94,
    "defect_count": 2,
    "issue_description": ""
  },
  {
    "delivery_id": "b9fb6257-7967-4a3e-b6d5-914b2ebbaa42",
    "vendor_id": "9f95005e-ad9e-473e-83a9-602256353a95",
    "vendor_name": "Advanced Safety Equipment - N",
    "delivery_date": "2025-12-04",
    "items_delivered": "Fire Hoses",
    "quantity": 155,
    "on_time_status": true,
    "quality_score": 4.37,
    "defect_count": 2,
    "issue_description": ""
  },
  {
    "delivery_id": "3f923b08-879f-451a-8b3e-448235cc8347",
    "vendor_id": "757511b3-18d6-46e9-8886-eddc26824fca",
    "vendor_name": "ProTech Safety Gear - W",
    "delivery_date": "2025-10-08",
    "items_delivered": "Safety Helmets",
    "quantity": 82,
    "on_time_status": false,
    "quality_score": 3.78,
    "defect_count": 1,
    "issue_description": "Delayed delivery"
  },
  {
    "delivery_id": "e66b3e40-6150-4f0d-a0b7-05c43bb77a59",
    "vendor_id": "27614199-6165-4d66-8642-981b0eb1efbe",
    "vendor_name": "Advanced Safety Equipment - B",
    "delivery_date": "2025-12-03",
    "items_delivered": "Fire Extinguishers",
    "quantity": 305,
    "on_time_status": false,
    "quality_score": 3.94,
    "defect_count": 0,
    "issue_description": "Incomplete order"
  },
  {
    "delivery_id": "63409384-3b90-4f57-a644-c7dd6bdaf84c",
    "vendor_id": "30ea2b71-2891-4974-a812-5b7e193dc75f",
    "vendor_name": "Guardian Safety Solutions - D",
    "delivery_date": "2025-06-26",
    "items_delivered": "Communication Equipment",
    "quantity": 34,
    "on_time_status": false,
    "quality_score": 4.74,
    "defect_count": 0,
    "issue_description": "Delayed delivery"
  },
  {
    "delivery_id": "b4fbc064-3564-42db-bb4b-b149ba0205ce",
    "vendor_id": "1cf99934-8e1b-4468-ad91-ac9f7506b9f7",
    "vendor_name": "Emergency Response Solutions - W",
    "delivery_date": "2025-06-24",
    "items_delivered": "Breathing Apparatus",
    "quantity": 352,
    "on_time_status": false,
    "quality_score": 4.17,
    "defect_count": 5,
    "issue_description": "No issues"
  },
  {
    "delivery_id": "0c3df5f6-7b20-479f-86ee-cafd874c36cf",
    "vendor_id": "7a522c24-b040-4be9-a9be-ac1b92af655a",
    "vendor_name": "Blaze Control Systems - C",
    "delivery_date": "2026-01-06",
    "items_delivered": "Breathing Apparatus",
    "quantity": 426,
    "on_time_status": true,
    "quality_score": 4.72,
    "defect_count": 0,
    "issue_description": ""
  },
  {
    "delivery_id": "e2bafe80-f648-4823-be3c-0cb68bb9cb23",
    "vendor_id": "a27beb2d-c353-4be0-9a4c-477a3faa45b5",
    "vendor_name": "Guardian Safety Solutions - F",
    "delivery_date": "2026-01-19",
    "items_delivered": "Fire Extinguishers",
    "quantity": 196,
    "on_time_status": false,
    "quality_score": 4.25,
    "defect_count": 2,
    "issue_description": "Incomplete order"
  },
  {
    "delivery_id": "ef58562f-3b36-4acf-8228-f74567a7531f",
    "vendor_id": "d61c486b-2ef6-4e9c-9827-fd910ac13c2b",
    "vendor_name": "RapidResponse Suppliers - A",
    "delivery_date": "2025-10-20",
    "items_delivered": "Protective Gear",
    "quantity": 185,
    "on_time_status": true,
    "quality_score": 3.56,
    "defect_count": 2,
    "issue_description": ""
  },
  {
    "delivery_id": "f6fd11af-bdb0-4c93-9041-286b6900e75c",
    "vendor_id": "9ca723b9-570c-4a06-91fa-34a7298caff8",
    "vendor_name": "FireSafe India Pvt Ltd - P",
    "delivery_date": "2025-09-08",
    "items_delivered": "Breathing Apparatus",
    "quantity": 141,
    "on_time_status": true,
    "quality_score": 3.71,
    "defect_count": 2,
    "issue_description": ""
  },
  {
    "delivery_id": "8aa9ce80-b16e-493d-ace2-d17293d69833",
    "vendor_id": "4ad1efb1-1e75-405a-b32d-370fd7d83754",
    "vendor_name": "Blaze Control Systems - R",
    "delivery_date": "2025-04-22",
    "items_delivered": "Protective Gear",
    "quantity": 474,
    "on_time_status": true,
    "quality_score": 3.69,
    "defect_count": 0,
    "issue_description": ""
  },
  {
    "delivery_id": "cb266bfc-a3bc-4a14-a3ba-ff30b65291f0",
    "vendor_id": "6f3192f1-370d-4a7b-88ad-f66768146458",
    "vendor_name": "Guardian Safety Solutions - Z",
    "delivery_date": "2025-07-19",
    "items_delivered": "Protective Gear",
    "quantity": 85,
    "on_time_status": true,
    "quality_score": 4.92,
    "defect_count": 1,
    "issue_description": ""
  },
  {
    "delivery_id": "a2b67664-dbf2-4730-8392-a046f83b965e",
    "vendor_id": "d61c486b-2ef6-4e9c-9827-fd910ac13c2b",
    "vendor_name": "RapidResponse Suppliers - A",
    "delivery_date": "2025-07-27",
    "items_delivered": "Protective Gear",
    "quantity": 483,
    "on_time_status": true,
    "quality_score": 3.55,
    "defect_count": 2,
    "issue_description": ""
  }
]